Workbook

Sheet Допущения
A1: Допущения модели TCO (все цены — вне источников: рыночные оценки РФ, 2026)
A3: Общие
A4: Количество магазинов | B4: 100 | C4: шт
A5: Страховые взносы работодателя | B5: 0.3 | C5: доля
A6: AS-IS (on-premise)
A7: Стоимость локального сервера | B7: 90000 | C7: руб/шт
A8: Доля парка серверов, заменяемая в год | B8: 0.25 | C8: доля/год
A9: Лицензии Windows Server + MS SQL (сопровождение) | B9: 45000 | C9: руб/маг/год
A10: Зарплата выездного ИТ-инженера (gross) | B10: 90000 | C10: руб/мес
A11: Норматив: магазинов на 1 выездного инженера | B11: 15 | C11: шт
A12: Командировочные/транспорт на инженера | B12: 150000 | C12: руб/год
A13: Интернет-канал магазина | B13: 3000 | C13: руб/мес
A14: Электропитание сервера | B14: 9000 | C14: руб/маг/год
A15: Аварийные замены (диски и пр.) | B15: 6000 | C15: руб/маг/год
A16: TO-BE (Cloud POS)
A17: Edge мини-ПК (Local Edge Node) | B17: 45000 | C17: руб/шт
A18: Планшет кассира | B18: 25000 | C18: руб/шт
A19: SaaS кассовое ПО | B19: 2500 | C19: руб/маг/мес
A20: Облачный бэкенд (Managed PG + compute), вся сеть | B20: 200000 | C20: руб/мес
A21: Зарплата DevOps-инженера (gross), 1 чел | B21: 200000 | C21: руб/мес
A22: Зарплата инженера поддержки (gross), 1 чел | B22: 120000 | C22: руб/мес
A23: Интернет основной + LTE-резерв | B23: 3800 | C23: руб/маг/мес
A24: Замена/ремонт edge-оборудования (с года 2) | B24: 0.05 | C24: доля CapEx/год
A25: Электропитание edge-узла (мини-ПК + планшет) | B25: 1200 | C25: руб/маг/год

Sheet TCO
A1: Расчёт TCO на 100 магазинов, руб.
A3: Статья затрат | B3: AS-IS Год 1 | C3: AS-IS Год 2 | D3: AS-IS Год 3 | E3: TO-BE Год 1 | F3: TO-BE Год 2 | G3: TO-BE Год 3
A4: Оборудование (CapEx) | B4: {='Допущения'!$B$4*'Допущения'!$B$8*'Допущения'!$B$7} -> 2250000 | C4: {='Допущения'!$B$4*'Допущения'!$B$8*'Допущения'!$B$7} -> 2250000 | D4: {='Допущения'!$B$4*'Допущения'!$B$8*'Допущения'!$B$7} -> 2250000 | E4: {='Допущения'!$B$4*('Допущения'!$B$17+'Допущения'!$B$18)} -> 7000000 | F4: 0 | G4: 0
A5: Лицензии / подписки (OpEx) | B5: {='Допущения'!$B$4*'Допущения'!$B$9} -> 4500000 | C5: {='Допущения'!$B$4*'Допущения'!$B$9} -> 4500000 | D5: {='Допущения'!$B$4*'Допущения'!$B$9} -> 4500000 | E5: {='Допущения'!$B$4*'Допущения'!$B$19*12} -> 3000000 | F5: {='Допущения'!$B$4*'Допущения'!$B$19*12} -> 3000000 | G5: {='Допущения'!$B$4*'Допущения'!$B$19*12} -> 3000000
A6: Облачная инфраструктура (OpEx) | B6: 0 | C6: 0 | D6: 0 | E6: {='Допущения'!$B$20*12} -> 2400000 | F6: {='Допущения'!$B$20*12} -> 2400000 | G6: {='Допущения'!$B$20*12} -> 2400000
A7: ФОТ поддержки (с взносами) | B7: {=ROUNDUP('Допущения'!$B$4/'Допущения'!$B$11,0)*('Допущения'!$B$10*12*(1+'Допущения'!$B$5)+'Допущения'!$B$12)} -> 10878000 | C7: {=ROUNDUP('Допущения'!$B$4/'Допущения'!$B$11,0)*('Допущения'!$B$10*12*(1+'Допущения'!$B$5)+'Допущения'!$B$12)} -> 10878000 | D7: {=ROUNDUP('Допущения'!$B$4/'Допущения'!$B$11,0)*('Допущения'!$B$10*12*(1+'Допущения'!$B$5)+'Допущения'!$B$12)} -> 10878000 | E7: {=('Допущения'!$B$21+'Допущения'!$B$22)*12*(1+'Допущения'!$B$5)} -> 4992000 | F7: {=('Допущения'!$B$21+'Допущения'!$B$22)*12*(1+'Допущения'!$B$5)} -> 4992000 | G7: {=('Допущения'!$B$21+'Допущения'!$B$22)*12*(1+'Допущения'!$B$5)} -> 4992000
A8: Каналы связи | B8: {='Допущения'!$B$4*'Допущения'!$B$13*12} -> 3600000 | C8: {='Допущения'!$B$4*'Допущения'!$B$13*12} -> 3600000 | D8: {='Допущения'!$B$4*'Допущения'!$B$13*12} -> 3600000 | E8: {='Допущения'!$B$4*'Допущения'!$B$23*12} -> 4560000 | F8: {='Допущения'!$B$4*'Допущения'!$B$23*12} -> 4560000 | G8: {='Допущения'!$B$4*'Допущения'!$B$23*12} -> 4560000
A9: Прочее (электропитание, аварийные замены) | B9: {='Допущения'!$B$4*('Допущения'!$B$14+'Допущения'!$B$15)} -> 1500000 | C9: {='Допущения'!$B$4*('Допущения'!$B$14+'Допущения'!$B$15)} -> 1500000 | D9: {='Допущения'!$B$4*('Допущения'!$B$14+'Допущения'!$B$15)} -> 1500000 | E9: {='Допущения'!$B$4*'Допущения'!$B$25} -> 120000 | F9: {='Допущения'!$B$4*('Допущения'!$B$25+('Допущения'!$B$17+'Допущения'!$B$18)*'Допущения'!$B$24)} -> 470000 | G9: {='Допущения'!$B$4*('Допущения'!$B$25+('Допущения'!$B$17+'Допущения'!$B$18)*'Допущения'!$B$24)} -> 470000
A10: ИТОГО за год | B10: {=SUM(B4:B9)} -> 22728000 | C10: {=SUM(C4:C9)} -> 22728000 | D10: {=SUM(D4:D9)} -> 22728000 | E10: {=SUM(E4:E9)} -> 22072000 | F10: {=SUM(F4:F9)} -> 15422000 | G10: {=SUM(G4:G9)} -> 15422000
A11: ИТОГО за 3 года | B11: {=SUM(B10:D10)} -> 68184000 | E11: {=SUM(E10:G10)} -> 52916000

Sheet Сравнение и ROI
A1: Сравнение сценариев и точка окупаемости
A3: TCO AS-IS за 3 года, руб | B3: {='TCO'!B11} -> 68184000
A4: TCO TO-BE за 3 года, руб | B4: {='TCO'!E11} -> 52916000
A5: Экономия за 3 года, руб | B5: {=B3-B4} -> 15268000
A6: Экономия за 3 года, % | B6: {=B5/B3} -> 0.2239235
A7: Годовые затраты AS-IS (run-rate), руб | B7: {='TCO'!B10} -> 22728000
A8: Годовые затраты TO-BE с года 2 (run-rate), руб | B8: {='TCO'!F10} -> 15422000
A9: Снижение годовых затрат (run-rate), % | B9: {=(B7-B8)/B7} -> 0.32145371
A10: Разовый CapEx TO-BE (год 1), руб | B10: {='TCO'!E4} -> 7000000
A11: Экономия OpEx в месяц, руб | B11: {=(B7-B8)/12} -> 608833.33
A12: Break-even, месяцев | B12: {=B10/B11} -> 11.497399
A14: Break-even учитывает только стоимость владения (без затрат на внедрение и миграцию — вне scope по условию).
